quanta/__init__.py
quanta/interpreter.py
quantum_interpreter-0.1.1.dist-info/METADATA
quantum_interpreter-0.1.1.dist-info/WHEEL
quantum_interpreter-0.1.1.dist-info/top_level.txt
quantum_interpreter-0.1.1.dist-info/RECORD
