Metadata-Version: 2.1
Name: quantum_interpreter
Version: 0.1.1
Summary: A Python library for interpreting natural language commands into Qiskit quantum circuits.
Classifier: Programming Language :: Python :: 3
Classifier: License :: OSI Approved :: MIT License
Classifier: Operating System :: OS Independent
Requires-Python: >=3.6
Requires-Dist: qiskit
